{
 "emails": [
  "michaelludwig@google.com"
 ],
 "author": {
  "2023-12-14T21:07:28Z": [
   "kylechar"
  ],
  "2023-12-08T19:02:50Z": [
   "kylechar"
  ],
  "2023-12-07T19:49:24Z": [
   "xiyuan",
   "kylechar"
  ],
  "2023-11-30T19:12:56Z": [
   "michellegc",
   "kylechar",
   "sky"
  ],
  "2023-11-16T22:40:32Z": [
   "xiyuan"
  ],
  "2023-11-09T23:32:26Z": [
   "xiyuan",
   "andrewxu",
   "sunnyps"
  ],
  "2023-11-09T02:38:03Z": [
   "wangxianzhu",
   "katie"
  ],
  "2023-10-31T15:32:33Z": [
   "andrewxu",
   "xiyuan"
  ],
  "2023-10-26T14:33:00Z": [
   "kylechar",
   "andrewxu",
   "xiyuan"
  ],
  "2023-10-11T20:52:28Z": [
   "robertphillips"
  ],
  "2023-10-02T15:00:47Z": [
   "vasilyt",
   "afakhry"
  ],
  "2023-09-28T19:46:25Z": [
   "afakhry"
  ],
  "2023-09-28T04:48:55Z": [
   "brianosman"
  ],
  "2023-09-06T02:00:02Z": [
   "robertphillips",
   "sunnyps",
   "sky"
  ],
  "2023-08-31T22:40:34Z": [
   "sky"
  ],
  "2023-08-29T01:00:01Z": [
   "hitawala",
   "sunnyps"
  ],
  "2023-08-03T19:07:31Z": [
   "robertphillips"
  ],
  "2023-07-14T17:17:43Z": [
   "robertphillips"
  ],
  "2023-07-11T15:03:43Z": [
   "robertphillips"
  ],
  "2023-06-30T19:08:58Z": [
   "dbaron"
  ],
  "2023-06-29T17:31:04Z": [
   "robertphillips"
  ],
  "2023-06-29T17:19:58Z": [
   "robertphillips",
   "vasilyt"
  ],
  "2023-06-29T15:59:41Z": [
   "vasilyt"
  ],
  "2023-06-28T19:20:13Z": [
   "dbaron"
  ],
  "2023-06-26T15:43:37Z": [
   "robertphillips"
  ],
  "2023-06-16T17:37:04Z": [
   "robertphillips"
  ],
  "2023-06-15T19:52:22Z": [
   "robertphillips"
  ],
  "2023-06-14T19:22:14Z": [
   "robertphillips"
  ],
  "2023-06-13T22:59:38Z": [
   "brianosman",
   "thestig"
  ],
  "2023-06-12T20:23:13Z": [
   "junov",
   "kylechar"
  ],
  "2023-06-09T18:53:25Z": [
   "vasilyt"
  ],
  "2023-06-09T18:32:17Z": [
   "danakj",
   "kylechar",
   "vasilyt"
  ],
  "2023-06-08T22:00:47Z": [
   "vasilyt"
  ],
  "2023-06-08T13:50:26Z": [
   "vasilyt"
  ],
  "2023-06-07T22:55:58Z": [
   "brianosman"
  ],
  "2023-06-07T13:42:37Z": [
   "kylechar"
  ],
  "2023-05-31T14:54:32Z": [
   "brianosman",
   "robertphillips"
  ],
  "2023-05-30T22:46:30Z": [
   "robertphillips"
  ],
  "2023-05-25T13:02:13Z": [
   "brianosman"
  ],
  "2023-05-23T15:24:48Z": [],
  "2023-05-23T14:55:54Z": [
   "zmin",
   "vasilyt"
  ],
  "2023-05-22T15:28:45Z": [
   "robertphillips"
  ],
  "2023-05-22T15:07:40Z": [
   "robertphillips"
  ],
  "2023-05-19T18:54:35Z": [
   "ritikagup",
   "kylechar"
  ],
  "2023-05-19T15:55:48Z": [
   "kylechar",
   "michaelludwig"
  ],
  "2023-05-19T15:35:42Z": [
   "robertphillips"
  ],
  "2023-05-19T13:33:48Z": [
   "robertphillips",
   "kylechar"
  ],
  "2023-05-18T14:02:36Z": [
   "robertphillips"
  ],
  "2023-05-16T20:43:22Z": [
   "robertphillips"
  ],
  "2023-05-15T16:32:20Z": [
   "robertphillips"
  ],
  "2023-05-03T18:08:59Z": [
   "robertphillips"
  ],
  "2022-11-14T19:33:06Z": [
   "kylechar"
  ],
  "2022-10-28T20:16:44Z": [
   "brianosman"
  ],
  "2022-10-28T17:11:40Z": [
   "kylechar"
  ],
  "2022-10-19T20:41:23Z": [
   "bsalomon"
  ],
  "2022-08-25T00:56:34Z": [
   "robertphillips"
  ],
  "2022-08-23T13:58:23Z": [
   "brianosman"
  ],
  "2022-08-19T20:48:46Z": [
   "brianosman"
  ],
  "2022-08-09T00:42:51Z": [
   "aaronhk",
   "kylechar"
  ],
  "2022-07-21T16:03:33Z": [
   "robertphillips"
  ],
  "2022-07-14T14:17:33Z": [
   "robertphillips"
  ],
  "2022-05-11T15:31:28Z": [
   "robertphillips"
  ],
  "2022-04-27T14:55:33Z": [
   "egdaniel"
  ],
  "2022-04-26T22:03:16Z": [
   "bsalomon"
  ],
  "2022-04-26T14:50:46Z": [
   "egdaniel"
  ],
  "2022-04-20T20:13:47Z": [
   "robertphillips",
   "bsalomon"
  ],
  "2022-03-31T17:58:58Z": [
   "bsalomon"
  ],
  "2022-03-21T17:46:27Z": [
   "kylechar",
   "bsheedy"
  ],
  "2022-03-18T18:28:43Z": [
   "robertphillips"
  ],
  "2022-03-17T20:48:32Z": [
   "kylechar",
   "bsheedy"
  ],
  "2022-03-03T21:54:07Z": [
   "fmalita"
  ],
  "2022-02-22T15:33:58Z": [
   "robertphillips"
  ],
  "2022-02-17T16:25:38Z": [
   "fmalita"
  ],
  "2022-02-16T22:27:23Z": [
   "robertphillips",
   "fmalita"
  ],
  "2022-02-16T21:36:43Z": [
   "robertphillips"
  ],
  "2021-11-30T18:30:10Z": [
   "bsalomon",
   "kylechar"
  ],
  "2021-11-29T20:15:39Z": [
   "weiliangc"
  ],
  "2021-09-29T13:24:59Z": [
   "vasilyt"
  ],
  "2021-09-14T19:18:25Z": [
   "robertphillips"
  ],
  "2021-08-31T14:48:39Z": [
   "fmalita",
   "robertphillips"
  ],
  "2021-07-14T14:19:45Z": [
   "kylechar"
  ],
  "2021-06-29T16:43:05Z": [
   "weiliangc"
  ],
  "2021-06-21T17:06:46Z": [
   "vasilyt"
  ],
  "2021-06-16T16:04:10Z": [
   "dbaron"
  ],
  "2021-06-11T13:55:16Z": [
   "vasilyt"
  ],
  "2021-06-10T14:43:11Z": [
   "robertphillips",
   "vasilyt"
  ],
  "2021-06-03T14:50:06Z": [
   "vasilyt"
  ],
  "2021-06-02T20:19:02Z": [
   "vasilyt"
  ],
  "2021-06-02T14:26:36Z": [
   "vasilyt"
  ],
  "2021-05-26T20:36:23Z": [
   "vasilyt"
  ],
  "2021-05-25T18:55:19Z": [
   "fmalita"
  ],
  "2021-05-19T16:29:34Z": [
   "robertphillips"
  ],
  "2021-05-17T23:20:31Z": [
   "wangxianzhu"
  ],
  "2021-05-11T21:16:41Z": [
   "vasilyt"
  ],
  "2021-05-11T13:17:56Z": [
   "vasilyt"
  ],
  "2021-04-28T19:29:18Z": [
   "vasilyt"
  ],
  "2021-04-28T15:52:27Z": [
   "dcheng",
   "schenney",
   "vasilyt"
  ],
  "2021-04-27T13:57:32Z": [
   "aaronhk",
   "vasilyt"
  ],
  "2021-04-20T15:49:24Z": [
   "vasilyt"
  ],
  "2021-04-19T18:09:15Z": [
   "vasilyt",
   "dcheng",
   "schenney"
  ],
  "2021-04-16T17:46:24Z": [
   "vasilyt",
   "schenney"
  ],
  "2021-04-06T13:48:25Z": [
   "vasilyt"
  ],
  "2021-04-05T16:15:08Z": [
   "michaelludwig",
   "chrishtr"
  ],
  "2021-03-30T15:37:42Z": [
   "weiliangc"
  ],
  "2021-03-29T14:44:33Z": [
   "vasilyt"
  ],
  "2021-03-24T20:02:20Z": [
   "hypan"
  ],
  "2021-03-24T19:00:37Z": [
   "vasilyt"
  ],
  "2021-03-24T16:32:22Z": [
   "vasilyt"
  ],
  "2021-03-23T14:26:20Z": [
   "vasilyt"
  ],
  "2021-03-19T18:34:49Z": [
   "vasilyt",
   "sunnyps"
  ],
  "2021-03-18T18:59:22Z": [
   "vmpstr",
   "xidachen"
  ],
  "2021-03-10T21:27:31Z": [
   "kylechar"
  ],
  "2021-02-06T14:45:36Z": [
   "kylechar",
   "vasilyt"
  ],
  "2021-01-26T01:58:58Z": [
   "sadrul",
   "sky"
  ],
  "2021-01-25T16:14:21Z": [
   "fmalita"
  ],
  "2021-01-22T17:46:41Z": [
   "fmalita"
  ],
  "2021-01-13T16:55:04Z": [
   "vasilyt",
   "danakj"
  ],
  "2021-01-13T03:10:47Z": [
   "danakj",
   "sky",
   "dcheng",
   "fserb",
   "fmalita"
  ],
  "2020-12-30T20:05:30Z": [
   "danakj"
  ],
  "2020-12-29T21:44:25Z": [
   "danakj"
  ],
  "2020-12-04T01:05:36Z": [
   "fs"
  ],
  "2020-11-22T19:46:59Z": [
   "fmalita"
  ],
  "2020-11-06T15:19:26Z": [
   "robertphillips",
   "fmalita"
  ],
  "2020-10-31T00:12:36Z": [
   "fmalita"
  ],
  "2020-10-13T15:52:00Z": [
   "masonfreed",
   "danakj",
   "penghuang"
  ],
  "2020-10-09T15:25:35Z": [
   "fmalita"
  ],
  "2020-10-05T19:47:53Z": [
   "robertphillips"
  ],
  "2020-09-25T21:31:51Z": [
   "jam"
  ],
  "2020-09-25T17:26:22Z": [
   "bsalomon",
   "robertphillips"
  ],
  "2020-09-15T22:45:05Z": [
   "robertphillips"
  ],
  "2020-07-20T16:43:11Z": [
   "fmalita"
  ],
  "2020-07-17T19:10:32Z": [
   "weiliangc"
  ],
  "2020-06-24T15:01:17Z": [
   "fmalita"
  ],
  "2020-06-22T14:05:45Z": [
   "michaelludwig",
   "fmalita"
  ],
  "2020-06-19T17:24:04Z": [
   "fmalita"
  ],
  "2020-06-11T23:49:35Z": [
   "sunnyps"
  ],
  "2020-06-02T18:52:51Z": [
   "jonross"
  ],
  "2020-05-28T16:52:07Z": [
   "fmalita"
  ],
  "2020-03-31T14:04:29Z": [
   "miersh"
  ],
  "2020-02-25T00:10:38Z": [
   "weiliangc"
  ],
  "2020-02-13T17:58:12Z": [
   "flackr"
  ],
  "2020-02-11T17:53:42Z": [
   "fmalita"
  ],
  "2020-02-07T18:46:52Z": [
   "fmalita"
  ],
  "2020-02-04T15:24:14Z": [
   "fmalita"
  ],
  "2020-01-25T18:31:23Z": [
   "fmalita"
  ],
  "2020-01-24T23:05:10Z": [
   "khushalsagar"
  ],
  "2020-01-24T18:40:52Z": [
   "backer"
  ],
  "2020-01-24T17:36:22Z": [
   "robertphillips"
  ],
  "2020-01-24T15:13:58Z": [
   "robertphillips",
   "fmalita"
  ],
  "2020-01-24T01:25:37Z": [
   "khushalsagar",
   "fmalita"
  ],
  "2019-12-04T21:31:59Z": [
   "weiliangc"
  ],
  "2019-12-03T23:04:16Z": [
   "weiliangc"
  ],
  "2019-11-21T21:35:33Z": [
   "backer",
   "kylechar"
  ],
  "2019-11-05T18:28:32Z": [
   "weiliangc"
  ],
  "2019-11-05T16:12:40Z": [
   "weiliangc"
  ],
  "2019-10-28T15:02:35Z": [
   "weiliangc"
  ],
  "2019-10-25T17:30:23Z": [
   "weiliangc"
  ],
  "2019-10-24T22:13:59Z": [
   "weiliangc"
  ],
  "2019-10-23T21:27:07Z": [
   "weiliangc"
  ],
  "2019-10-21T22:45:30Z": [
   "weiliangc"
  ],
  "2019-10-21T16:29:50Z": [
   "weiliangc"
  ],
  "2019-10-17T21:07:58Z": [
   "weiliangc"
  ],
  "2019-10-15T21:05:30Z": [
   "weiliangc"
  ],
  "2019-10-15T20:43:25Z": [
   "weiliangc"
  ],
  "2019-10-03T14:27:57Z": [
   "backer"
  ],
  "2019-09-05T23:54:30Z": [
   "weiliangc"
  ],
  "2019-09-05T22:25:22Z": [
   "kylechar"
  ],
  "2019-09-05T15:03:42Z": [
   "kylechar"
  ],
  "2019-07-31T22:02:57Z": [
   "enne"
  ],
  "2019-07-19T20:37:17Z": [
   "robertphillips"
  ],
  "2019-07-19T15:23:53Z": [
   "fmalita"
  ],
  "2019-07-11T16:21:54Z": [
   "fmalita"
  ],
  "2019-07-09T21:24:39Z": [
   "weiliangc"
  ],
  "2019-07-09T17:19:19Z": [
   "fmalita"
  ],
  "2019-07-08T16:04:15Z": [
   "fmalita"
  ],
  "2019-06-20T16:25:26Z": [
   "bsalomon",
   "fmalita"
  ],
  "2019-06-19T18:23:33Z": [
   "fmalita"
  ],
  "2019-05-31T20:58:11Z": [
   "weiliangc"
  ],
  "2019-05-31T20:34:03Z": [
   "weiliangc"
  ],
  "2019-05-31T20:07:23Z": [
   "weiliangc"
  ],
  "2019-05-16T14:28:31Z": [
   "masonfreed",
   "backer"
  ],
  "2019-05-06T17:49:17Z": [
   "weiliangc"
  ],
  "2019-04-24T13:38:19Z": [
   "weiliangc"
  ],
  "2019-04-17T15:30:54Z": [
   "backer",
   "weiliangc"
  ],
  "2019-04-15T18:30:27Z": [
   "weiliangc",
   "backer"
  ],
  "2019-04-15T16:23:39Z": [
   "weiliangc"
  ],
  "2019-04-09T15:15:19Z": [
   "weiliangc",
   "masonfreed"
  ],
  "2019-04-04T15:56:53Z": [
   "backer"
  ],
  "2019-04-01T21:55:34Z": [
   "weiliangc"
  ],
  "2019-04-01T18:06:43Z": [
   "weiliangc"
  ],
  "2019-04-01T15:35:31Z": [
   "weiliangc"
  ],
  "2019-03-29T22:27:46Z": [
   "weiliangc"
  ],
  "2019-03-29T20:45:35Z": [
   "weiliangc",
   "sgilhuly"
  ],
  "2019-03-27T18:02:09Z": [
   "weiliangc",
   "backer"
  ],
  "2019-03-27T16:33:41Z": [
   "weiliangc"
  ],
  "2019-03-27T15:17:39Z": [
   "weiliangc"
  ],
  "2019-03-26T13:03:37Z": [
   "weiliangc"
  ],
  "2019-02-06T14:08:35Z": [
   "kbr"
  ],
  "2019-01-31T20:42:36Z": [
   "enne"
  ],
  "2019-01-30T20:04:02Z": [
   "enne"
  ],
  "2019-01-02T22:28:15Z": [
   "kbr"
  ],
  "2018-12-27T16:41:35Z": [
   "fmalita"
  ],
  "2018-12-26T15:47:17Z": [
   "kbr"
  ],
  "2018-12-21T22:59:56Z": [
   "fmalita"
  ],
  "2018-12-21T15:56:46Z": [
   "bsalomon",
   "reed"
  ],
  "2018-12-17T20:53:15Z": [
   "kbr"
  ],
  "2018-12-17T18:37:47Z": [
   "fmalita"
  ],
  "2018-12-12T21:28:24Z": [
   "fmalita"
  ],
  "2018-12-11T16:02:47Z": [
   "bsalomon",
   "fmalita"
  ],
  "2018-12-04T14:57:22Z": [
   "fmalita"
  ],
  "2018-12-03T16:03:56Z": [
   "fmalita"
  ],
  "2018-11-28T17:56:02Z": [
   "fmalita"
  ],
  "2018-11-27T02:51:16Z": [
   "fmalita"
  ],
  "2018-11-12T16:48:26Z": [
   "fmalita"
  ],
  "2018-11-08T19:45:56Z": [
   "fmalita"
  ],
  "2018-10-11T18:04:45Z": [
   "bsalomon",
   "weiliangc"
  ],
  "2018-09-24T22:47:24Z": [
   "bsalomon",
   "robertphillips",
   "fmalita"
  ],
  "2024-02-06T15:23:38Z": [
   "robertphillips"
  ],
  "2024-02-16T20:08:33Z": [
   "flackr",
   "kylechar"
  ],
  "2024-02-14T16:56:27Z": [
   "robertphillips"
  ],
  "2024-02-14T14:46:45Z": [
   "brianosman"
  ],
  "2024-02-21T16:16:34Z": [
   "brianosman"
  ],
  "2024-02-20T22:47:19Z": [
   "brianosman"
  ],
  "2024-03-06T18:36:49Z": [
   "robertphillips"
  ],
  "2024-03-15T17:28:02Z": [
   "hitawala"
  ],
  "2024-03-25T14:23:54Z": [
   "khaslett"
  ]
 },
 "review": {
  "2024-02-03T02:24:54Z": "nemco",
  "2024-02-01T21:38:15Z": "hitawala",
  "2024-02-01T15:23:23Z": "hitawala",
  "2024-01-23T17:55:57Z": "lehoangquyen",
  "2023-12-20T15:08:00Z": "blundell",
  "2023-12-11T18:50:46Z": "khaslett",
  "2023-11-23T07:45:22Z": "jie.a.chen",
  "2023-11-10T17:49:11Z": "vollick",
  "2023-11-03T17:31:11Z": "jvanverth",
  "2023-11-01T15:56:11Z": "avi",
  "2023-09-18T23:25:50Z": "jonross",
  "2023-09-13T17:52:52Z": "hitawala",
  "2023-09-08T16:25:01Z": "robertphillips",
  "2023-09-06T14:55:45Z": "robertphillips",
  "2023-08-31T20:45:19Z": "hitawala",
  "2023-08-29T01:23:27Z": "hitawala",
  "2023-08-25T16:57:21Z": "johnstiles",
  "2023-08-22T02:16:01Z": "johnstiles",
  "2023-08-21T23:33:16Z": "hitawala",
  "2023-08-21T18:46:11Z": "sukoo",
  "2023-06-29T23:12:50Z": "wangxianzhu",
  "2023-06-23T21:46:14Z": "kylechar",
  "2023-06-20T14:34:09Z": "kylechar",
  "2023-06-02T01:58:39Z": "sunnyps",
  "2023-05-26T02:28:27Z": "wangxianzhu",
  "2023-05-25T13:27:05Z": "penghuang",
  "2023-05-19T15:55:48Z": "michaelludwig",
  "2023-05-17T09:41:09Z": "blundell",
  "2023-05-16T07:17:06Z": "blundell",
  "2023-04-26T13:48:41Z": "kylechar",
  "2023-04-25T18:32:51Z": "kylechar",
  "2023-04-21T20:28:29Z": "kylechar",
  "2023-04-21T15:22:22Z": "brianosman",
  "2023-04-21T15:21:08Z": "brianosman",
  "2023-04-19T21:00:36Z": "brianosman",
  "2023-03-30T19:20:21Z": "brianosman",
  "2022-12-12T17:56:12Z": "kylechar",
  "2022-11-10T16:09:48Z": "brianosman",
  "2022-10-12T17:24:08Z": "khushalsagar",
  "2022-09-29T20:37:53Z": "brianosman",
  "2022-09-07T16:24:10Z": "rebecca.chang",
  "2022-09-01T17:17:30Z": "egdaniel",
  "2022-08-31T15:27:15Z": "egdaniel",
  "2022-08-29T18:12:27Z": "kylechar",
  "2022-08-05T20:54:00Z": "brianosman",
  "2022-08-02T17:00:54Z": "brianosman",
  "2022-07-19T20:15:58Z": "pdr",
  "2022-05-13T23:18:03Z": "bialpio",
  "2022-04-15T00:47:30Z": "bsalomon",
  "2022-04-11T16:59:31Z": "bsalomon",
  "2022-04-06T16:11:26Z": "bsalomon",
  "2022-04-01T21:43:32Z": "hob",
  "2022-03-31T15:59:29Z": "bsalomon",
  "2022-02-18T01:36:01Z": "kylechar",
  "2022-02-16T21:23:22Z": "kylechar",
  "2022-02-16T14:02:03Z": "kylechar",
  "2021-11-11T16:06:04Z": "linnan",
  "2021-11-05T22:25:09Z": "brianosman",
  "2021-08-09T19:34:02Z": "bsalomon",
  "2021-08-04T23:33:53Z": "csmartdalton",
  "2021-07-31T18:10:03Z": "csmartdalton",
  "2021-06-04T01:25:24Z": "rbpotter",
  "2021-04-15T14:42:38Z": "brianosman",
  "2021-04-05T16:15:08Z": "michaelludwig",
  "2021-03-22T19:25:17Z": "hypan",
  "2021-03-04T14:48:49Z": "bsalomon",
  "2021-02-22T21:40:11Z": "bsalomon",
  "2021-02-16T15:15:58Z": "reed",
  "2021-02-01T16:41:51Z": "reed",
  "2021-01-12T22:11:16Z": "kylechar",
  "2020-12-09T15:19:15Z": "kylechar",
  "2020-11-17T16:18:39Z": "robertphillips",
  "2020-11-16T20:57:42Z": "mabian",
  "2020-10-09T21:35:29Z": "bsalomon",
  "2020-10-08T17:44:32Z": "herb",
  "2020-06-22T14:05:45Z": "michaelludwig",
  "2020-06-13T00:52:21Z": "reed",
  "2020-05-01T22:18:12Z": "bsalomon",
  "2020-04-24T13:47:23Z": "bsalomon",
  "2020-04-16T17:42:37Z": "bsalomon",
  "2020-04-10T23:21:16Z": "bungeman",
  "2019-11-15T15:16:56Z": "brianosman",
  "2024-02-06T22:28:46Z": "hitawala",
  "2024-02-23T22:54:51Z": "johnstiles",
  "2024-02-21T19:09:01Z": "johnstiles",
  "2024-02-26T15:37:13Z": "jpgravel",
  "2024-02-28T20:35:54Z": "brianosman",
  "2024-03-05T16:27:08Z": "brianosman",
  "2024-03-04T15:53:34Z": "johnstiles"
 }
}