{
 "author": {
  "2023-11-28T15:57:37Z": [
   "dmercadier@chromium.org"
  ],
  "2023-07-24T13:39:57Z": [
   "thibaudm@chromium.org",
   "ahaas@chromium.org"
  ],
  "2023-07-24T10:46:09Z": [
   "dmercadier@chromium.org",
   "ahaas@chromium.org"
  ],
  "2023-07-20T10:04:23Z": [
   "dmercadier@chromium.org",
   "ahaas@chromium.org"
  ],
  "2023-05-03T14:16:00Z": [
   "jkummerow@chromium.org",
   "thibaudm@chromium.org"
  ],
  "2023-03-31T14:43:55Z": [
   "thibaudm@chromium.org",
   "ahaas@chromium.org"
  ],
  "2023-04-05T10:39:36Z": [
   "clemensb@chromium.org",
   "mseaborn@chromium.org"
  ],
  "2023-03-31T09:35:47Z": [
   "clemensb@chromium.org"
  ],
  "2022-11-11T10:13:46Z": [
   "clemensb@chromium.org"
  ],
  "2021-04-29T10:25:52Z": [
   "ahaas@chromium.org",
   "neis@chromium.org"
  ],
  "2021-03-31T09:47:43Z": [
   "jgruber@chromium.org",
   "ahaas@chromium.org"
  ],
  "2021-03-24T11:14:27Z": [
   "ahaas@chromium.org",
   "neis@chromium.org"
  ],
  "2024-02-19T18:17:19Z": [
   "dmercadier@chromium.org",
   "victorgomes@chromium.org"
  ],
  "2024-03-04T11:16:27Z": [
   "mliedtke@chromium.org"
  ],
  "2024-03-13T13:33:11Z": [
   "mliedtke@chromium.org"
  ],
  "2024-03-12T11:39:54Z": [
   "mliedtke@chromium.org"
  ]
 },
 "review": {}
}