{
 "author": {
  "2024-01-29T14:39:37Z": [
   "dcheng@chromium.org",
   "boliu@chromium.org"
  ],
  "2023-12-02T17:38:41Z": [
   "reillyg@chromium.org",
   "dcheng@chromium.org",
   "boliu@chromium.org",
   "caseq@chromium.org"
  ],
  "2023-11-06T15:54:59Z": [
   "dsv@chromium.org"
  ],
  "2023-10-13T15:18:31Z": [
   "futhark@chromium.org",
   "jonross@chromium.org"
  ],
  "2023-07-20T19:59:44Z": [
   "almaher@microsoft.com"
  ],
  "2023-07-19T14:43:50Z": [
   "almaher@microsoft.com",
   "jonross@chromium.org",
   "dcheng@chromium.org",
   "reillyg@chromium.org",
   "grt@chromium.org"
  ],
  "2021-07-29T12:18:39Z": [
   "reillyg@chromium.org",
   "boliu@chromium.org",
   "dcheng@chromium.org"
  ],
  "2021-07-21T11:50:26Z": [
   "reillyg@chromium.org",
   "boliu@chromium.org",
   "haraken@chromium.org"
  ],
  "2021-07-20T03:56:41Z": [
   "ericwilligers@chromium.org",
   "boliu@chromium.org",
   "dcheng@chromium.org",
   "reillyg@chromium.org"
  ],
  "2021-07-17T04:10:33Z": [
   "dcheng@chromium.org",
   "reillyg@chromium.org",
   "creis@chromium.org",
   "sadrul@chromium.org",
   "tkent@chromium.org"
  ],
  "2021-03-16T16:04:46Z": [
   "futhark@chromium.org"
  ],
  "2020-12-04T01:01:39Z": [
   "futhark@chromium.org"
  ],
  "2019-08-05T21:26:56Z": [
   "bajones@chromium.org",
   "kbr@chromium.org"
  ],
  "2024-02-26T21:25:19Z": [
   "bokan@chromium.org",
   "boliu@chromium.org",
   "dcheng@chromium.org"
  ],
  "2024-03-08T22:51:34Z": [
   "raphael.kubo.da.costa@intel.com",
   "reillyg@chromium.org"
  ],
  "2024-03-06T18:01:56Z": [
   "bokan@chromium.org",
   "futhark@chromium.org"
  ],
  "2024-03-06T14:06:46Z": [
   "futhark@chromium.org",
   "dcheng@chromium.org"
  ]
 },
 "review": {
  "2023-12-15T18:57:47Z": "qingxinwu@google.com"
 }
}