{
 "author": {
  "2018-05-01T01:06:44Z": [
   "xiaohuic@chromium.org"
  ],
  "2018-04-05T17:34:39Z": [
   "xiaohuic@chromium.org"
  ],
  "2018-03-29T18:39:51Z": [
   "dcheng@chromium.org",
   "xiyuan@chromium.org",
   "xiaohuic@chromium.org"
  ],
  "2018-03-23T00:26:14Z": [
   "xiaohuic@chromium.org"
  ],
  "2018-03-22T19:32:38Z": [
   "xiaohuic@chromium.org"
  ],
  "2018-03-22T01:37:48Z": [
   "xiaohuic@chromium.org"
  ],
  "2018-03-08T23:55:17Z": [
   "xiaohuic@chromium.org"
  ]
 },
 "review": {}
}