{
 "author": {
  "2022-08-05T12:26:06Z": [
   "swestphal@chromium.org"
  ],
  "2022-07-29T17:04:48Z": [
   "zmin@chromium.org",
   "torne@chromium.org"
  ],
  "2022-07-15T16:12:36Z": [
   "torne@chromium.org"
  ],
  "2022-07-14T17:52:17Z": [
   "torne@chromium.org"
  ],
  "2022-06-27T17:05:48Z": [
   "torne@chromium.org",
   "battre@chromium.org",
   "tedchoc@chromium.org"
  ],
  "2022-06-23T21:57:29Z": [
   "swestphal@chromium.org",
   "torne@chromium.org"
  ],
  "2022-04-08T12:54:36Z": [
   "zmin@chromium.org",
   "torne@chromium.org",
   "boliu@chromium.org"
  ]
 },
 "review": {}
}