{
 "author": {
  "2023-06-02T14:25:32Z": [
   "stefanoduo@google.com"
  ],
  "2023-05-10T10:44:23Z": [
   "stefanoduo@google.com"
  ],
  "2023-05-03T09:42:35Z": [
   "stefanoduo@google.com"
  ],
  "2023-04-04T15:25:02Z": [
   "stefanoduo@google.com"
  ],
  "2023-03-30T14:02:31Z": [
   "stefanoduo@google.com"
  ],
  "2023-01-12T09:32:17Z": [
   "agrieve@chromium.org",
   "stefanoduo@google.com"
  ],
  "2023-01-09T11:59:07Z": [
   "stefanoduo@google.com"
  ],
  "2023-01-04T00:50:46Z": [
   "stefanoduo@google.com"
  ],
  "2022-12-21T23:16:21Z": [
   "stefanoduo@google.com"
  ],
  "2022-12-21T12:08:59Z": [
   "stefanoduo@google.com"
  ],
  "2022-12-20T12:43:50Z": [
   "stefanoduo@google.com"
  ],
  "2022-12-05T15:14:22Z": [
   "stefanoduo@google.com"
  ],
  "2022-12-05T13:01:53Z": [
   "stefanoduo@google.com"
  ],
  "2022-11-30T17:19:26Z": [
   "stefanoduo@google.com",
   "dschinazi@chromium.org"
  ],
  "2022-11-28T20:34:31Z": [
   "stefanoduo@google.com",
   "pkasting@chromium.org"
  ],
  "2022-11-25T09:41:45Z": [
   "stefanoduo@google.com"
  ],
  "2022-10-27T12:44:42Z": [
   "stefanoduo@google.com"
  ],
  "2022-09-30T15:17:58Z": [
   "stefanoduo@google.com"
  ],
  "2022-09-28T08:33:48Z": [
   "stefanoduo@google.com"
  ],
  "2022-09-22T18:38:09Z": [
   "gbeaty@google.com"
  ],
  "2022-09-22T15:46:35Z": [
   "agrieve@chromium.org"
  ],
  "2022-09-16T16:00:25Z": [
   "stefanoduo@google.com"
  ],
  "2022-09-16T13:57:40Z": [
   "stefanoduo@google.com"
  ],
  "2022-09-15T08:42:27Z": [
   "stefanoduo@google.com"
  ],
  "2022-09-07T14:32:07Z": [
   "stefanoduo@google.com"
  ],
  "2022-08-25T13:04:37Z": [
   "stefanoduo@google.com"
  ],
  "2022-03-01T10:41:03Z": [
   "torne@chromium.org"
  ],
  "2022-02-09T14:21:39Z": [
   "thakis@chromium.org"
  ],
  "2022-01-10T18:55:08Z": [
   "torne@chromium.org"
  ],
  "2021-11-10T16:17:37Z": [
   "hazems@chromium.org"
  ],
  "2021-08-18T14:53:20Z": [
   "torne@chromium.org"
  ],
  "2021-07-21T10:48:37Z": [
   "dschinazi@chromium.org"
  ],
  "2021-06-09T17:32:54Z": [
   "torne@chromium.org"
  ],
  "2021-06-07T16:31:45Z": [
   "govind@chromium.org"
  ],
  "2021-05-25T16:30:35Z": [
   "benmason@chromium.org"
  ],
  "2021-05-25T08:13:10Z": [
   "torne@chromium.org"
  ],
  "2021-05-17T16:52:27Z": [
   "torne@chromium.org"
  ],
  "2021-05-13T19:28:23Z": [
   "gbeaty@chromium.org"
  ],
  "2021-05-12T11:28:48Z": [
   "torne@chromium.org"
  ],
  "2021-05-11T12:33:01Z": [
   "torne@chromium.org"
  ],
  "2021-05-11T10:44:11Z": [
   "rch@chromium.org"
  ],
  "2021-05-10T10:21:34Z": [
   "torne@chromium.org"
  ]
 },
 "review": {
  "2023-05-17T11:19:51Z": "stefanoduo@google.com",
  "2023-05-15T13:57:14Z": "stefanoduo@google.com",
  "2023-05-15T13:48:59Z": "stefanoduo@google.com",
  "2023-05-15T13:12:08Z": "stefanoduo@google.com",
  "2023-05-15T13:03:21Z": "stefanoduo@google.com",
  "2023-05-15T10:45:03Z": "stefanoduo@google.com",
  "2023-05-15T10:35:39Z": "stefanoduo@google.com",
  "2023-05-15T10:32:48Z": "colibie@google.com",
  "2023-05-15T10:25:33Z": "stefanoduo@google.com",
  "2023-05-15T10:02:26Z": "stefanoduo@google.com",
  "2023-05-15T09:54:11Z": "stefanoduo@google.com",
  "2023-05-12T15:38:59Z": "stefanoduo@google.com",
  "2023-05-11T11:42:50Z": "aymanm@google.com",
  "2023-05-10T16:07:09Z": "colibie@google.com",
  "2023-05-10T11:34:48Z": "colibie@google.com",
  "2023-05-09T17:16:15Z": "stefanoduo@google.com",
  "2023-05-09T16:38:23Z": "aymanm@google.com",
  "2023-05-09T16:34:06Z": "stefanoduo@google.com",
  "2023-05-09T12:23:01Z": "stefanoduo@google.com",
  "2023-05-09T12:20:42Z": "stefanoduo@google.com",
  "2023-05-09T11:36:16Z": "stefanoduo@google.com",
  "2023-05-09T11:34:54Z": "stefanoduo@google.com",
  "2023-05-04T16:18:29Z": "stefanoduo@google.com",
  "2023-05-04T11:18:01Z": "stefanoduo@google.com",
  "2023-04-25T15:48:33Z": "stefanoduo@google.com",
  "2023-04-25T15:32:13Z": "stefanoduo@google.com",
  "2023-04-13T14:26:05Z": "stefanoduo@google.com"
 }
}