{
 "author": {
  "2020-07-18T01:30:49Z": [
   "agl@chromium.org"
  ],
  "2020-06-20T01:23:21Z": [
   "reillyg@chromium.org"
  ],
  "2020-06-18T22:54:31Z": [
   "brucedawson@chromium.org"
  ],
  "2020-06-16T17:25:51Z": [
   "reillyg@chromium.org"
  ],
  "2020-05-18T22:52:34Z": [
   "agl@chromium.org"
  ],
  "2020-05-11T23:43:37Z": [
   "agl@chromium.org"
  ],
  "2020-04-17T18:26:57Z": [
   "martinkr@chromium.org"
  ],
  "2020-04-16T22:37:44Z": [
   "reillyg@chromium.org"
  ],
  "2020-03-10T05:46:45Z": [
   "avi@chromium.org",
   "agl@chromium.org"
  ],
  "2020-01-31T01:08:52Z": [
   "ortuno@chromium.org"
  ],
  "2020-01-30T18:17:15Z": [
   "reillyg@chromium.org"
  ],
  "2020-01-28T20:27:39Z": [
   "odejesush@chromium.org",
   "reillyg@chromium.org"
  ],
  "2020-01-24T23:43:42Z": [
   "agl@chromium.org"
  ],
  "2020-01-24T23:04:55Z": [
   "agl@chromium.org"
  ],
  "2019-09-19T21:12:29Z": [
   "agl@chromium.org"
  ],
  "2019-09-14T00:00:50Z": [
   "nsatragno@chromium.org",
   "agl@chromium.org"
  ],
  "2019-09-12T00:38:42Z": [
   "jam@chromium.org",
   "nsatragno@chromium.org"
  ],
  "2019-09-03T19:33:56Z": [
   "agl@chromium.org"
  ],
  "2019-08-30T19:35:38Z": [
   "dbeam@chromium.org",
   "agl@chromium.org"
  ],
  "2019-08-30T16:45:50Z": [
   "agl@chromium.org",
   "jam@chromium.org"
  ],
  "2019-08-29T18:44:44Z": [
   "agl@chromium.org"
  ],
  "2019-08-20T21:45:57Z": [
   "agl@chromium.org"
  ],
  "2019-08-20T00:48:46Z": [
   "agl@chromium.org"
  ],
  "2019-07-24T01:37:27Z": [
   "nsatragno@chromium.org",
   "avi@chromium.org"
  ],
  "2019-07-19T19:27:22Z": [
   "avi@chromium.org",
   "agl@chromium.org"
  ],
  "2019-07-17T17:57:39Z": [
   "nsatragno@chromium.org"
  ],
  "2019-06-28T01:54:46Z": [
   "agl@chromium.org"
  ],
  "2019-05-13T23:19:27Z": [
   "martinkr@chromium.org"
  ],
  "2019-05-07T22:55:00Z": [
   "agl@chromium.org"
  ],
  "2019-04-08T19:39:19Z": [
   "agl@chromium.org"
  ],
  "2019-04-02T20:47:42Z": [
   "martinkr@google.com"
  ],
  "2019-02-09T01:21:52Z": [
   "agl@chromium.org"
  ],
  "2019-02-08T20:27:42Z": [
   "kpaulhamus@chromium.org"
  ],
  "2019-02-08T02:42:07Z": [
   "kpaulhamus@chromium.org"
  ],
  "2019-01-23T17:23:17Z": [
   "agl@chromium.org"
  ],
  "2019-01-17T01:21:28Z": [
   "dcheng@chromium.org",
   "agl@chromium.org"
  ],
  "2018-12-12T21:08:02Z": [
   "agl@chromium.org"
  ],
  "2018-12-05T02:56:44Z": [
   "agl@chromium.org"
  ],
  "2018-12-03T21:20:30Z": [
   "agl@chromium.org"
  ],
  "2018-11-30T21:42:23Z": [
   "agl@chromium.org"
  ],
  "2018-11-30T20:19:34Z": [
   "agl@chromium.org"
  ],
  "2018-11-30T03:34:02Z": [
   "agl@chromium.org"
  ],
  "2018-11-30T02:55:14Z": [
   "agl@chromium.org"
  ],
  "2018-11-29T20:58:27Z": [
   "agl@chromium.org"
  ],
  "2018-11-29T04:16:16Z": [
   "agl@chromium.org"
  ],
  "2018-11-29T00:09:04Z": [
   "agl@chromium.org"
  ],
  "2018-11-21T08:10:12Z": [
   "agl@chromium.org",
   "kpaulhamus@chromium.org"
  ],
  "2018-11-20T07:11:55Z": [
   "agl@chromium.org",
   "kpaulhamus@chromium.org"
  ],
  "2018-11-16T02:10:43Z": [
   "kpaulhamus@chromium.org",
   "dcheng@chromium.org",
   "agl@chromium.org"
  ],
  "2018-11-14T21:26:33Z": [
   "hongjunchoi@chromium.org",
   "agl@chromium.org"
  ],
  "2018-11-13T03:14:00Z": [
   "hongjunchoi@chromium.org"
  ],
  "2018-11-10T02:11:47Z": [
   "kpaulhamus@chromium.org"
  ],
  "2018-11-09T22:31:00Z": [
   "agl@chromium.org"
  ],
  "2018-11-09T21:39:47Z": [
   "kpaulhamus@chromium.org"
  ],
  "2018-11-09T18:58:13Z": [
   "agl@chromium.org"
  ],
  "2018-11-09T03:02:37Z": [
   "agl@chromium.org"
  ],
  "2018-11-09T01:15:57Z": [
   "agl@chromium.org"
  ],
  "2018-11-08T00:43:36Z": [
   "hongjunchoi@chromium.org",
   "agl@chromium.org"
  ],
  "2018-11-06T02:02:50Z": [
   "rockot@google.com",
   "agl@chromium.org",
   "kpaulhamus@chromium.org"
  ],
  "2018-11-02T21:34:32Z": [
   "agl@chromium.org"
  ],
  "2018-11-02T01:43:15Z": [
   "kpaulhamus@chromium.org"
  ],
  "2018-10-31T22:09:48Z": [
   "wfh@chromium.org",
   "agl@chromium.org"
  ]
 },
 "review": {
  "2020-04-17T18:26:57Z": "martinkr@chromium.org",
  "2019-05-13T23:19:27Z": "martinkr@chromium.org",
  "2019-02-05T23:33:29Z": "sdefresne@chromium.org",
  "2018-10-29T21:23:31Z": "agl@chromium.org",
  "2018-08-14T20:35:44Z": "engedy@chromium.org"
 }
}