{
 "emails": [
  "gurmeetk@google.com"
 ],
 "author": {
  "2024-02-01T18:33:04Z": [
   "twellington",
   "wenyufu"
  ],
  "2023-12-13T00:51:04Z": [
   "twellington",
   "elijahtaylor"
  ],
  "2023-09-06T08:09:05Z": [
   "twellington",
   "yusukes",
   "skavuluru"
  ],
  "2023-08-15T17:51:39Z": [
   "yusukes",
   "skavuluru",
   "twellington"
  ],
  "2023-08-08T19:37:55Z": [
   "twellington",
   "yusukes",
   "skavuluru"
  ],
  "2023-07-17T18:14:15Z": [
   "yusukes",
   "twellington"
  ],
  "2023-07-10T20:12:02Z": [
   "yusukes",
   "twellington"
  ],
  "2023-07-06T22:34:45Z": [
   "twellington",
   "yusukes"
  ],
  "2023-07-05T18:43:50Z": [
   "twellington"
  ],
  "2023-06-27T17:05:27Z": [
   "twellington"
  ],
  "2023-06-22T15:39:33Z": [
   "twellington"
  ],
  "2023-06-15T21:36:27Z": [
   "yusukes",
   "twellington"
  ],
  "2023-06-12T17:21:39Z": [
   "yusukes",
   "twellington"
  ],
  "2023-06-09T01:59:31Z": [
   "twellington",
   "yusukes"
  ],
  "2024-02-13T00:19:05Z": [
   "twellington",
   "wenyufu"
  ]
 },
 "review": {}
}