{
 "author": {
  "2021-05-27T13:33:40Z": [
   "sebsg@chromium.org",
   "bokan@chromium.org"
  ],
  "2021-05-26T13:40:14Z": [
   "kmilka@chromium.org",
   "bokan@chromium.org"
  ],
  "2021-04-30T23:01:19Z": [
   "bokan@chromium.org"
  ],
  "2021-04-21T20:50:58Z": [
   "gayane@chromium.org",
   "bokan@chromium.org"
  ],
  "2021-04-20T15:49:13Z": [
   "bokan@chromium.org"
  ],
  "2021-03-17T14:36:01Z": [
   "yosin@chromium.org",
   "bokan@chromium.org"
  ],
  "2021-03-12T22:57:14Z": [
   "bokan@chromium.org",
   "mpearson@chromium.org"
  ],
  "2021-03-11T23:27:53Z": [
   "sky@chromium.org",
   "palmer@chromium.org",
   "bokan@chromium.org"
  ],
  "2021-03-10T17:59:12Z": [
   "palmer@chromium.org",
   "johntlee@chromium.org",
   "bokan@chromium.org",
   "sky@chromium.org"
  ],
  "2021-03-10T01:08:50Z": [
   "bokan@chromium.org"
  ],
  "2021-03-04T06:04:21Z": [
   "bokan@chromium.org",
   "mpearson@chromium.org"
  ],
  "2021-03-02T17:56:44Z": [
   "bokan@chromium.org"
  ],
  "2021-02-27T00:29:00Z": [
   "palmer@chromium.org",
   "sky@chromium.org",
   "bokan@chromium.org"
  ],
  "2021-02-24T03:04:30Z": [
   "bokan@chromium.org"
  ],
  "2021-02-22T20:41:48Z": [
   "bokan@chromium.org"
  ],
  "2021-02-10T15:23:02Z": [
   "rakina@chromium.org",
   "bokan@chromium.org"
  ],
  "2021-02-05T15:09:39Z": [
   "gayane@chromium.org",
   "bokan@chromium.org"
  ],
  "2021-02-05T02:22:16Z": [
   "bokan@chromium.org"
  ],
  "2021-01-14T22:42:42Z": [
   "bokan@chromium.org"
  ],
  "2020-12-03T19:13:09Z": [
   "bokan@chromium.org",
   "masonfreed@chromium.org"
  ],
  "2020-11-24T23:25:53Z": [
   "bokan@chromium.org"
  ],
  "2020-11-13T20:09:29Z": [
   "bokan@chromium.org"
  ],
  "2020-11-04T17:57:39Z": [
   "sebsg@chromium.org",
   "sky@chromium.org"
  ],
  "2020-10-27T13:39:29Z": [
   "sky@chromium.org",
   "bokan@chromium.org",
   "johntlee@chromium.org"
  ],
  "2020-10-15T17:42:54Z": [
   "kmilka@chromium.org",
   "bokan@chromium.org",
   "sebsg@chromium.org"
  ],
  "2020-10-14T21:27:04Z": [
   "bokan@chromium.org"
  ],
  "2020-10-08T23:31:15Z": [
   "bokan@chromium.org"
  ],
  "2020-10-02T17:13:43Z": [
   "manukh@chromium.org",
   "battre@chromium.org",
   "rkaplow@chromium.org",
   "bokan@chromium.org",
   "sebsg@chromium.org"
  ],
  "2020-10-01T16:58:51Z": [
   "bokan@chromium.org"
  ],
  "2020-10-01T16:44:56Z": [
   "yosin@chromium.org",
   "bokan@chromium.org"
  ],
  "2020-09-28T16:24:59Z": [
   "gayane@chromium.org"
  ],
  "2020-09-26T19:15:09Z": [
   "bokan@chromium.org"
  ],
  "2020-09-25T13:43:52Z": [
   "bokan@chromium.org"
  ],
  "2020-09-18T17:16:00Z": [
   "yosin@chromium.org",
   "bokan@chromium.org",
   "tmartino@chromium.org"
  ],
  "2020-09-16T16:01:33Z": [
   "bokan@chromium.org",
   "yosin@chromium.org",
   "tmartino@chromium.org"
  ],
  "2020-09-15T17:58:11Z": [
   "dcheng@chromium.org",
   "flackr@chromium.org"
  ],
  "2020-09-15T03:16:29Z": [
   "dcheng@chromium.org",
   "flackr@chromium.org",
   "gayane@chromium.org",
   "rockot@google.com"
  ],
  "2020-08-25T17:51:15Z": [
   "bokan@chromium.org",
   "gayane@chromium.org"
  ],
  "2020-08-17T15:25:33Z": [
   "yosin@chromium.org",
   "bokan@chromium.org"
  ],
  "2020-08-12T15:11:24Z": [
   "yosin@chromium.org",
   "bokan@chromium.org"
  ],
  "2020-08-12T06:07:30Z": [
   "bokan@chromium.org",
   "yosin@chromium.org"
  ],
  "2020-07-25T20:01:12Z": [
   "bokan@chromium.org"
  ]
 },
 "review": {
  "2021-06-14T19:15:20Z": "bokan@chromium.org",
  "2021-06-07T19:21:41Z": "bokan@chromium.org",
  "2021-06-02T17:14:54Z": "bokan@chromium.org",
  "2021-05-31T15:10:33Z": "bokan@chromium.org",
  "2021-05-18T17:11:56Z": "japhet@chromium.org",
  "2021-05-05T00:49:36Z": "kmilka@chromium.org",
  "2021-04-26T17:06:32Z": "cheickcisse@google.com",
  "2021-04-21T20:50:58Z": "gayane@chromium.org",
  "2021-03-11T05:53:27Z": "kmilka@chromium.org",
  "2021-02-05T15:09:39Z": "gayane@chromium.org",
  "2020-12-09T23:11:09Z": "masonfreed@chromium.org",
  "2020-12-01T17:09:07Z": "seblalancette@chromium.org",
  "2020-11-25T01:08:23Z": "seblalancette@chromium.org",
  "2020-11-24T00:58:57Z": "bokan@chromium.org",
  "2020-10-15T12:48:42Z": "sebsg@chromium.org",
  "2020-09-28T16:24:59Z": "gayane@chromium.org",
  "2020-09-15T03:16:29Z": "gayane@chromium.org",
  "2020-08-25T17:51:15Z": "gayane@chromium.org"
 }
}