{
 "author": {
  "2023-01-31T23:41:50Z": [
   "alcooper@chromium.org"
  ]
 },
 "review": {
  "2024-01-18T13:00:19Z": "kron@webrtc.org",
  "2023-09-21T21:13:50Z": "kron@webrtc.org",
  "2023-08-10T11:47:15Z": "kron@webrtc.org",
  "2023-05-23T16:14:46Z": "alcooper@chromium.org",
  "2023-02-08T22:16:01Z": "alcooper@chromium.org",
  "2022-10-27T08:11:01Z": "m.olbrich@pengutronix.de",
  "2022-10-25T18:34:45Z": "alcooper@chromium.org",
  "2022-10-18T12:27:17Z": "grulja@gmail.com",
  "2022-10-13T00:03:36Z": "lambroslambrou@chromium.org",
  "2022-09-28T16:43:53Z": "alcooper@chromium.org",
  "2022-09-08T21:42:17Z": "alcooper@chromium.org",
  "2022-09-02T18:09:00Z": "alcooper@chromium.org",
  "2022-08-31T22:01:51Z": "alcooper@chromium.org",
  "2022-08-31T17:31:11Z": "alcooper@chromium.org",
  "2022-08-30T09:35:49Z": "grulja@gmail.com",
  "2022-08-30T17:01:18Z": "alcooper@chromium.org",
  "2022-08-22T12:06:08Z": "grulja@gmail.com",
  "2022-08-18T21:07:16Z": "auorion@microsoft.com",
  "2022-07-27T00:00:18Z": "me@github.nico.onl",
  "2022-07-25T22:24:33Z": "pkasting@chromium.org",
  "2022-07-21T17:21:02Z": "auorion@microsoft.com",
  "2022-06-10T21:33:18Z": "rwkeane@google.com",
  "2022-06-10T07:21:48Z": "grulja@gmail.com",
  "2022-05-25T18:38:02Z": "pkasting@chromium.org",
  "2022-05-11T20:24:15Z": "avi@chromium.org",
  "2022-05-11T02:26:25Z": "tpearson@raptorcs.com",
  "2022-05-11T15:12:40Z": "avi@chromium.org",
  "2022-05-05T12:55:58Z": "grulja@gmail.com",
  "2022-03-23T08:34:51Z": "grulja@gmail.com",
  "2022-03-21T21:47:05Z": "alcooper@chromium.org",
  "2022-02-24T12:59:13Z": "nisse@webrtc.org",
  "2022-02-15T20:36:46Z": "grulja@gmail.com",
  "2022-02-15T19:05:57Z": "alcooper@chromium.org",
  "2022-02-11T15:01:08Z": "grulja@gmail.com",
  "2022-02-09T15:25:24Z": "salmanmalik@google.com",
  "2022-02-05T16:13:45Z": "grulja@gmail.com",
  "2022-02-07T12:10:15Z": "grulja@gmail.com",
  "2022-02-05T16:19:24Z": "grulja@gmail.com",
  "2022-02-04T20:51:10Z": "alcooper@chromium.org",
  "2022-02-03T23:59:42Z": "salmanmalik@google.com",
  "2022-01-28T20:23:20Z": "grulja@gmail.com",
  "2022-01-21T07:58:04Z": "grulja@gmail.com",
  "2022-01-14T15:15:28Z": "grulja@gmail.com",
  "2022-01-14T09:37:04Z": "grulja@gmail.com",
  "2021-12-14T08:17:04Z": "mbonadei@webrtc.org",
  "2021-12-09T08:57:56Z": "grulja@gmail.com",
  "2021-12-07T13:20:53Z": "grulja@gmail.com",
  "2021-12-06T10:30:09Z": "grulja@gmail.com",
  "2021-12-03T06:43:01Z": "grulja@gmail.com",
  "2021-12-02T06:35:46Z": "grulja@gmail.com",
  "2021-12-02T21:30:59Z": "alcooper@chromium.org",
  "2024-02-13T23:52:28Z": "sunggch@microsoft.com"
 }
}